python_thumbnails-0.5.1.dist-info/DESCRIPTION.rst
python_thumbnails-0.5.1.dist-info/METADATA
python_thumbnails-0.5.1.dist-info/metadata.json
python_thumbnails-0.5.1.dist-info/RECORD
python_thumbnails-0.5.1.dist-info/top_level.txt
python_thumbnails-0.5.1.dist-info/WHEEL
tests/__init__.py
tests/data.py
tests/django_settings.py
tests/test_cache_backends.py
tests/test_conf.py
tests/test_engines.py
tests/test_helpers.py
tests/test_images.py
tests/test_init.py
tests/test_storage_backends.py
tests/test_templatetags.py
tests/thumbnails_settings.py
tests/utils.py
thumbnails/__init__.py
thumbnails/cache_backends.py
thumbnails/errors.py
thumbnails/helpers.py
thumbnails/images.py
thumbnails/storage_backends.py
thumbnails/conf/__init__.py
thumbnails/conf/defaults.py
thumbnails/conf/defaults_django.py
thumbnails/conf/wrapper.py
thumbnails/engines/__init__.py
thumbnails/engines/base.py
thumbnails/engines/dummy.py
thumbnails/engines/pgmagick_engine.py
thumbnails/engines/pillow_engine.py
thumbnails/engines/wand_engine.py
thumbnails/templatetags/__init__.py
thumbnails/templatetags/thumbnails.py
