Metadata-Version: 2.0
Name: python-thumbnails
Version: 0.5.1
Summary: Thumbnails for Django, Flask and other Python projects.
Home-page: http://github.com/relekang/python-thumbnails
Author: Rolf Erik Lekang
Author-email: me@rolflekang.com
License: MIT
Platform: UNKNOWN
Classifier: Development Status :: 4 - Beta
Classifier: Programming Language :: Python
Classifier: Programming Language :: Python :: 3.4
Requires-Dist: six (==1.9.0)
Requires-Dist: requests (==2.6.0)
